fla/__init__.py
fla/utils.py
fla/modules/__init__.py
fla/modules/activations.py
fla/modules/convolution.py
fla/modules/feature_map.py
fla/modules/fused_bitlinear.py
fla/modules/fused_cross_entropy.py
fla/modules/fused_kl_div.py
fla/modules/fused_linear_cross_entropy.py
fla/modules/fused_norm_gate.py
fla/modules/grpo.py
fla/modules/l2norm.py
fla/modules/l2warp.py
fla/modules/layernorm.py
fla/modules/layernorm_gated.py
fla/modules/mlp.py
fla/modules/parallel.py
fla/modules/rotary.py
fla/modules/token_shift.py
fla/ops/__init__.py
fla/ops/abc/__init__.py
fla/ops/abc/chunk.py
fla/ops/abc/naive.py
fla/ops/attn/__init__.py
fla/ops/attn/decoding.py
fla/ops/attn/parallel.py
fla/ops/based/__init__.py
fla/ops/based/fused_chunk.py
fla/ops/based/naive.py
fla/ops/based/parallel.py
fla/ops/comba/__init__.py
fla/ops/comba/chunk.py
fla/ops/comba/fused_recurrent.py
fla/ops/comba/utils.py
fla/ops/comba/wy_fast.py
fla/ops/common/__init__.py
fla/ops/common/chunk_delta_h.py
fla/ops/common/chunk_h.py
fla/ops/common/chunk_h_parallel.py
fla/ops/common/chunk_h_split.py
fla/ops/common/chunk_o.py
fla/ops/common/chunk_scaled_dot_kkt.py
fla/ops/common/fused_chunk.py
fla/ops/common/fused_recurrent.py
fla/ops/delta_rule/__init__.py
fla/ops/delta_rule/chunk.py
fla/ops/delta_rule/fused_chunk.py
fla/ops/delta_rule/fused_recurrent.py
fla/ops/delta_rule/naive.py
fla/ops/delta_rule/parallel.py
fla/ops/delta_rule/wy_fast.py
fla/ops/deltaformer/__init__.py
fla/ops/deltaformer/invcum.py
fla/ops/deltaformer/naive.py
fla/ops/deltaformer/parallel.py
fla/ops/forgetting_attn/__init__.py
fla/ops/forgetting_attn/parallel.py
fla/ops/gated_delta_product/__init__.py
fla/ops/gated_delta_product/chunk.py
fla/ops/gated_delta_product/chunk_deltaproduct_h.py
fla/ops/gated_delta_product/chunk_deltaproduct_o.py
fla/ops/gated_delta_product/chunk_ref.py
fla/ops/gated_delta_product/naive.py
fla/ops/gated_delta_rule/__init__.py
fla/ops/gated_delta_rule/chunk.py
fla/ops/gated_delta_rule/fused_recurrent.py
fla_core-0.4.1.dist-info/licenses/LICENSE
fla_core-0.4.1.dist-info/METADATA
fla_core-0.4.1.dist-info/WHEEL
fla_core-0.4.1.dist-info/top_level.txt
fla_core-0.4.1.dist-info/RECORD
