Metadata-Version: 2.4
Name: fla-core
Version: 0.4.1
Summary: Core operations for flash-linear-attention
Project-URL: Homepage, https://github.com/fla-org/flash-linear-attention
Project-URL: Repository, https://github.com/fla-org/flash-linear-attention
Requires-Python: >=3.10
License-File: LICENSE
Requires-Dist: torch
Requires-Dist: einops
Dynamic: license-file
